Workbook
Name Slicer_Months__Date: #N/A
Name Slicer_Years__Date: #N/A

Sheet Index
I7: Index
I9: Pages | J9: Description
I11: V1 | J11: Raw Data
I12: V2 | J12: Somewhat clean (Remove Blank Rows)
I13: V3 | J13: Unique Retailers & Products (Analysis)
I14: V4 | J14: Final Clean
I15: V5 | J15: Pivots Table
I16: V6 | J16: Dashboard

Sheet V1
A1: Customer_ID | B1: Order_ID | C1: Product Name | D1: Units Sold | E1: Date | F1: Estimated Revenue | G1: Estimated Cost
A2: 3 | B2: 397386 | C2: White Chocolate Macadamia Nut | D2: 3997.5 | E2: 43831 | F2: 23985 | G2: 10993.125
A3: 5 | B3: 613058 | C3: White Chocolate Macadamia Nut | D3: 3864 | E3: 43922 | F3: 23184 | G3: 10626
A4: 4 | B4: 766402 | C4: White Chocolate Macadamia Nut | D4: 3850.5 | E4: 43922 | F4: 23103 | G4: 10588.875
A5: 4 | B5: 710702 | C5: White Chocolate Macadamia Nut | D5: 3793.5 | E5: 44013 | F5: 22761 | G5: 10432.125
A6: 5 | B6: 283378 | C6: Chocolate Chip | D6: 4492.5 | E6: 43922 | F6: 22462.5 | G6: 8985
A7: 3 | B7: 239419 | C7: Chocolate Chip | D7: 4251 | E7: 43831 | F7: 21255 | G7: 8502
A8: 4 | B8: 739483 | C8: Oatmeal Raisin | D8: 4219.5 | E8: 43922 | F8: 21097.5 | G8: 9282.9
A9: 3 | B9: 253399 | C9: Chocolate Chip | D9: 4026 | E9: 44013 | F9: 20130 | G9: 8052
A10: 4 | B10: 361305 | C10: Chocolate Chip | D10: 3945 | E10: 43831 | F10: 19725 | G10: 7890
A12: 2 | B12: 603195 | C12: Chocolate Chip | D12: 3801 | E12: 43922 | F12: 19005 | G12: 7602
A13: 2 | B13: 643111 | C13: Chocolate Chip | D13: 3675 | E13: 43922 | F13: 18375 | G13: 7350
A14: 4 | B14: 861720 | C14: White Chocolate Macadamia Nut | D14: 2966 | E14: 43739 | F14: 17796 | G14: 8156.5
... A707: 2 | B707: 205221 | C707: Fortune Cookie | D707: 200 | E707: 43952 | F707: 200 | G707: 100

Sheet V2
A1: Customer_ID | B1: Order_ID | C1: Product Name | D1: Units Sold | E1: Date | F1: Estimated Revenue | G1: Estimated Cost | H1: Cost per product | I1: Actual cost per product | J1: profit per product | K1: Gross Profit
A2: 3 | B2: 397386 | C2: White Chocolate Macadamia Nut | D2: 3997.5 | E2: 43831 | F2: 23985 | G2: 10993.125 | H2: =F2/D2 -> 6 | I2: =G2/D2 -> 2.75 | J2: =H2-I2 -> 3.25 | K2: =D2*J2 -> 12991.875
A3: 5 | B3: 613058 | C3: White Chocolate Macadamia Nut | D3: 3864 | E3: 43922 | F3: 23184 | G3: 10626 | H3: =F3/D3 -> 6 | I3: =G3/D3 -> 2.75 | J3: =H3-I3 -> 3.25 | K3: =D3*J3 -> 12558
A4: 4 | B4: 766402 | C4: White Chocolate Macadamia Nut | D4: 3850.5 | E4: 43922 | F4: 23103 | G4: 10588.875 | H4: =F4/D4 -> 6 | I4: =G4/D4 -> 2.75 | J4: =H4-I4 -> 3.25 | K4: =D4*J4 -> 12514.125
A5: 4 | B5: 710702 | C5: White Chocolate Macadamia Nut | D5: 3793.5 | E5: 44013 | F5: 22761 | G5: 10432.125 | H5: =F5/D5 -> 6 | I5: =G5/D5 -> 2.75 | J5: =H5-I5 -> 3.25 | K5: =D5*J5 -> 12328.875
A6: 5 | B6: 283378 | C6: Chocolate Chip | D6: 4492.5 | E6: 43922 | F6: 22462.5 | G6: 8985 | H6: =F6/D6 -> 5 | I6: =G6/D6 -> 2 | J6: =H6-I6 -> 3 | K6: =D6*J6 -> 13477.5
A7: 3 | B7: 239419 | C7: Chocolate Chip | D7: 4251 | E7: 43831 | F7: 21255 | G7: 8502 | H7: =F7/D7 -> 5 | I7: =G7/D7 -> 2 | J7: =H7-I7 -> 3 | K7: =D7*J7 -> 12753
A8: 4 | B8: 739483 | C8: Oatmeal Raisin | D8: 4219.5 | E8: 43922 | F8: 21097.5 | G8: 9282.9 | H8: =F8/D8 -> 5 | I8: =G8/D8 -> 2.2 | J8: =H8-I8 -> 2.8 | K8: =D8*J8 -> 11814.6
A9: 3 | B9: 253399 | C9: Chocolate Chip | D9: 4026 | E9: 44013 | F9: 20130 | G9: 8052 | H9: =F9/D9 -> 5 | I9: =G9/D9 -> 2 | J9: =H9-I9 -> 3 | K9: =D9*J9 -> 12078
A10: 4 | B10: 361305 | C10: Chocolate Chip | D10: 3945 | E10: 43831 | F10: 19725 | G10: 7890 | H10: =F10/D10 -> 5 | I10: =G10/D10 -> 2 | J10: =H10-I10 -> 3 | K10: =D10*J10 -> 11835
A11: 2 | B11: 603195 | C11: Chocolate Chip | D11: 3801 | E11: 43922 | F11: 19005 | G11: 7602 | H11: =F11/D11 -> 5 | I11: =G11/D11 -> 2 | J11: =H11-I11 -> 3 | K11: =D11*J11 -> 11403
A12: 2 | B12: 643111 | C12: Chocolate Chip | D12: 3675 | E12: 43922 | F12: 18375 | G12: 7350 | H12: =F12/D12 -> 5 | I12: =G12/D12 -> 2 | J12: =H12-I12 -> 3 | K12: =D12*J12 -> 11025
A13: 4 | B13: 861720 | C13: White Chocolate Macadamia Nut | D13: 2966 | E13: 43739 | F13: 17796 | G13: 8156.5 | H13: =F13/D13 -> 6 | I13: =G13/D13 -> 2.75 | J13: =H13-I13 -> 3.25 | K13: =D13*J13 -> 9639.5
... A701: 2 | B701: 205221 | C701: Fortune Cookie | D701: 200 | E701: 43952 | F701: 200 | G701: 100 | H701: =F701/D701 -> 1 | I701: =G701/D701 -> 0.5 | J701: =H701-I701 -> 0.5 | K701: =D701*J701 -> 100

Sheet V3
C4: Retailers ID | E4: Product Name | F4: Product Cost | G4: Actual Cost | H4: Profit | I4: Total Profit | J4: Total Product | K4: Total Revenue | L4: Total Orders
C5: {=_xlfn._xlws.SORT(_xlfn.UNIQUE('V2'!A2:A701))} -> 1 | E5: {=_xlfn.UNIQUE('V2'!C2:C701)} -> White Chocolate Macadamia Nut | F5: =VLOOKUP(E5,'V2'!C$1:H$701,6,FALSE) -> 6 | G5: =VLOOKUP(E5,'V2'!C$1:I$701,7,FALSE) -> 2.75 | H5: =VLOOKUP(E5,'V2'!C$1:J$701,8,FALSE) -> 3.25 | I5: =SUMIF('V2'!C$2:C$701,'V3'!E5,'V2'!K$2:K$701) -> 527879.62 | J5: =SUMIF('V2'!C$2:C$701,'V3'!E5,'V2'!D$2:D$701) -> 162424.5 | K5: =SUMIF('V2'!C$2:C$701,'V3'!E5,'V2'!F$2:F$701) -> 974547 | L5: =COUNTIF('V2'!C$2:C$701,'V3'!E5) -> 109 | N5: No of Retailers | O5: =COUNTA(_xlfn.ANCHORARRAY(C5)) -> 5
C6: 2 | E6: Chocolate Chip | F6: =VLOOKUP(E6,'V2'!C$1:H$701,6,FALSE) -> 5 | G6: =VLOOKUP(E6,'V2'!C$1:I$701,7,FALSE) -> 2 | H6: =VLOOKUP(E6,'V2'!C$1:J$701,8,FALSE) -> 3 | I6: =SUMIF('V2'!C$2:C$701,'V3'!E6,'V2'!K$2:K$701) -> 1014718.5 | J6: =SUMIF('V2'!C$2:C$701,'V3'!E6,'V2'!D$2:D$701) -> 338239.5 | K6: =SUMIF('V2'!C$2:C$701,'V3'!E6,'V2'!F$2:F$701) -> 1691197.5 | L6: =COUNTIF('V2'!C$2:C$701,'V3'!E6) -> 202 | N6: No of Products | O6: =COUNTA(_xlfn.ANCHORARRAY(E5)) -> 6
C7: 3 | E7: Oatmeal Raisin | F7: =VLOOKUP(E7,'V2'!C$1:H$701,6,FALSE) -> 5 | G7: =VLOOKUP(E7,'V2'!C$1:I$701,7,FALSE) -> 2.2 | H7: =VLOOKUP(E7,'V2'!C$1:J$701,8,FALSE) -> 2.8 | I7: =SUMIF('V2'!C$2:C$701,'V3'!E7,'V2'!K$2:K$701) -> 434882 | J7: =SUMIF('V2'!C$2:C$701,'V3'!E7,'V2'!D$2:D$701) -> 155315 | K7: =SUMIF('V2'!C$2:C$701,'V3'!E7,'V2'!F$2:F$701) -> 776575 | L7: =COUNTIF('V2'!C$2:C$701,'V3'!E7) -> 94
C8: 4 | E8: Snickerdoodle | F8: =VLOOKUP(E8,'V2'!C$1:H$701,6,FALSE) -> 4 | G8: =VLOOKUP(E8,'V2'!C$1:I$701,7,FALSE) -> 1.5 | H8: =VLOOKUP(E8,'V2'!C$1:J$701,8,FALSE) -> 2.5 | I8: =SUMIF('V2'!C$2:C$701,'V3'!E8,'V2'!K$2:K$701) -> 367115 | J8: =SUMIF('V2'!C$2:C$701,'V3'!E8,'V2'!D$2:D$701) -> 146846 | K8: =SUMIF('V2'!C$2:C$701,'V3'!E8,'V2'!F$2:F$701) -> 587384 | L8: =COUNTIF('V2'!C$2:C$701,'V3'!E8) -> 93
C9: 5 | E9: Sugar | F9: =VLOOKUP(E9,'V2'!C$1:H$701,6,FALSE) -> 3 | G9: =VLOOKUP(E9,'V2'!C$1:I$701,7,FALSE) -> 1.25 | H9: =VLOOKUP(E9,'V2'!C$1:J$701,8,FALSE) -> 1.75 | I9: =SUMIF('V2'!C$2:C$701,'V3'!E9,'V2'!K$2:K$701) -> 295370.25 | J9: =SUMIF('V2'!C$2:C$701,'V3'!E9,'V2'!D$2:D$701) -> 168783 | K9: =SUMIF('V2'!C$2:C$701,'V3'!E9,'V2'!F$2:F$701) -> 506349 | L9: =COUNTIF('V2'!C$2:C$701,'V3'!E9) -> 109
E10: Fortune Cookie | F10: =VLOOKUP(E10,'V2'!C$1:H$701,6,FALSE) -> 1 | G10: =VLOOKUP(E10,'V2'!C$1:I$701,7,FALSE) -> 0.5 | H10: =VLOOKUP(E10,'V2'!C$1:J$701,8,FALSE) -> 0.5 | I10: =SUMIF('V2'!C$2:C$701,'V3'!E10,'V2'!K$2:K$701) -> 77099 | J10: =SUMIF('V2'!C$2:C$701,'V3'!E10,'V2'!D$2:D$701) -> 154198 | K10: =SUMIF('V2'!C$2:C$701,'V3'!E10,'V2'!F$2:F$701) -> 154198 | L10: =COUNTIF('V2'!C$2:C$701,'V3'!E10) -> 93

Sheet V4
A1: Retailers_ID | B1: Order_ID | C1: Product Name | D1: Units Sold | E1: Date | F1: Estimated Revenue | G1: Estimated Cost Price | H1: Profit Margin
A2: 3 | B2: 397386 | C2: White Chocolate Macadamia Nut | D2: 3998 | E2: 43831 | F2: 23985 | G2: 10993.13 | H2: 54.17
A3: 5 | B3: 613058 | C3: White Chocolate Macadamia Nut | D3: 3864 | E3: 43922 | F3: 23184 | G3: 10626 | H3: 54.17
A4: 4 | B4: 766402 | C4: White Chocolate Macadamia Nut | D4: 3851 | E4: 43922 | F4: 23103 | G4: 10588.88 | H4: 54.17
A5: 4 | B5: 710702 | C5: White Chocolate Macadamia Nut | D5: 3794 | E5: 44013 | F5: 22761 | G5: 10432.13 | H5: 54.17
A6: 5 | B6: 283378 | C6: Chocolate Chip | D6: 4493 | E6: 43922 | F6: 22462.5 | G6: 8985 | H6: 60
A7: 3 | B7: 239419 | C7: Chocolate Chip | D7: 4251 | E7: 43831 | F7: 21255 | G7: 8502 | H7: 60
A8: 4 | B8: 739483 | C8: Oatmeal Raisin | D8: 4220 | E8: 43922 | F8: 21097.5 | G8: 9282.9 | H8: 56
A9: 3 | B9: 253399 | C9: Chocolate Chip | D9: 4026 | E9: 44013 | F9: 20130 | G9: 8052 | H9: 60
A10: 4 | B10: 361305 | C10: Chocolate Chip | D10: 3945 | E10: 43831 | F10: 19725 | G10: 7890 | H10: 60
A11: 2 | B11: 603195 | C11: Chocolate Chip | D11: 3801 | E11: 43922 | F11: 19005 | G11: 7602 | H11: 60
A12: 2 | B12: 643111 | C12: Chocolate Chip | D12: 3675 | E12: 43922 | F12: 18375 | G12: 7350 | H12: 60
A13: 4 | B13: 861720 | C13: White Chocolate Macadamia Nut | D13: 2966 | E13: 43739 | F13: 17796 | G13: 8156.5 | H13: 54.17
... A701: 2 | B701: 205221 | C701: Fortune Cookie | D701: 200 | E701: 43952 | F701: 200 | G701: 100 | H701: 50

Sheet V5
U2: Retailers Pivot Table
U5: (Revenue vs Profit) per Order | Y5: Product Sold | AB5: Retailers Profit Margin | AE5: Product Profit | AH5: Unit Sold vs Profit
C6: Average of Profit Margin | E6: Sum of Units Sold | F6: Count of Order_ID | G6: Average Unit Sold per Order | I6: Row Labels | J6: Sum of Units Sold | L6: Sum of Estimated Profit | N6: Sum of Units Sold | P6: Sum of Estimated Profit | Q6: Count of Order_ID | R6: Profit per Order | U6: Row Labels | V6: Revenue | W6: Profit | Y6: Row Labels | Z6: Sum of Units Sold | AB6: Row Labels | AC6: Average of Profit Margin | AE6: Row Labels | AF6: Sum of Estimated Profit | AH6: Row Labels | AI6: Units Sold by Retailers | AJ6: Profit by Retailers
C7: 57.298571 | E7: 1125824 | F7: 700 | G7: =GETPIVOTDATA("Sum of Units Sold",$E$6)/GETPIVOTDATA("Count of Order_ID",$E$6) -> 1608.32 | I7: Chocolate Chip | J7: 338243 | L7: 2717064.4 | N7: 1125824 | P7: 2717064.4 | Q7: 700 | R7: =GETPIVOTDATA("Sum of Estimated Profit",$P$6)/GETPIVOTDATA("Count of Order_ID",$P$6) -> 3881.5206 | U7: Chocolate Chip | V7: 8372.2649 | W7: 5023.3589 | Y7: Chocolate Chip | Z7: 338243 | AB7: 1 | AC7: 57.273696 | AE7: Chocolate Chip | AF7: 1014718.5 | AH7: 1 | AI7: 128772 | AJ7: 302197.39
I8: Grand Total | J8: 338243 | U8: Fortune Cookie | V8: 1658.043 | W8: 829.02151 | Y8: Fortune Cookie | Z8: 154201 | AB8: 2 | AC8: 57.124848 | AE8: Fortune Cookie | AF8: 77099 | AH8: 2 | AI8: 221026 | AJ8: 523315.44
C9: =ROUND(GETPIVOTDATA("Profit Margin",$C$6),2) -> 57.3 | U9: Oatmeal Raisin | V9: 8261.4362 | W9: 4626.4043 | Y9: Oatmeal Raisin | Z9: 155318 | AB9: 3 | AC9: 57.320485 | AE9: Oatmeal Raisin | AF9: 434882 | AH9: 3 | AI9: 329681 | AJ9: 828377.41
G10: =G7 -> 1608.32 | L10: =GETPIVOTDATA("Estimated Profit",$L$6) -> 2717064.4 | U10: Snickerdoodle | V10: 6315.957 | W10: 3947.4731 | Y10: Snickerdoodle | Z10: 146849 | AB10: 4 | AC10: 57.232051 | AE10: Snickerdoodle | AF10: 367115 | AH10: 4 | AI10: 266896 | AJ10: 639674.56
U11: Sugar | V11: 4645.4037 | W11: 2709.8192 | Y11: Sugar | Z11: 168787 | AB11: 5 | AC11: 57.571228 | AE11: Sugar | AF11: 295370.29 | AH11: 5 | AI11: 179449 | AJ11: 423499.63
U12: White Chocolate Macadamia Nut | V12: 8940.7982 | W12: 4842.9325 | Y12: White Chocolate Macadamia Nut | Z12: 162426 | AB12: Grand Total | AC12: 57.298571 | AE12: White Chocolate Macadamia Nut | AF12: 527879.64 | AH12: Grand Total | AI12: 1125824 | AJ12: 2717064.4
U13: Grand Total | V13: 6700.3579 | W13: 3881.5206 | Y13: Grand Total | Z13: 1125824 | AE13: Grand Total | AF13: 2717064.4
Y17: =Y6 -> Row Labels | Z17: =Z6 -> Sum of Units Sold
Y18: =Y7 -> Chocolate Chip | Z18: =GETPIVOTDATA("Units Sold",$Y$6,"Product Name",Y18) -> 338243
Y19: =Y8 -> Fortune Cookie | Z19: =GETPIVOTDATA("Units Sold",$Y$6,"Product Name",Y19) -> 154201
Y20: =Y9 -> Oatmeal Raisin | Z20: =GETPIVOTDATA("Units Sold",$Y$6,"Product Name",Y20) -> 155318
Y21: =Y10 -> Snickerdoodle | Z21: =GETPIVOTDATA("Units Sold",$Y$6,"Product Name",Y21) -> 146849
Y22: =Y11 -> Sugar | Z22: =GETPIVOTDATA("Units Sold",$Y$6,"Product Name",Y22) -> 168787
Y23: =Y12 -> White Chocolate Macadamia Nut | Z23: =GETPIVOTDATA("Units Sold",$Y$6,"Product Name",Y23) -> 162426

Sheet V6
